discogs_client/__init__.py
discogs_client/client.py
discogs_client/exceptions.py
discogs_client/fetchers.py
discogs_client/models.py
discogs_client/utils.py
python3_discogs_client-2.7.1.dist-info/LICENSE
python3_discogs_client-2.7.1.dist-info/METADATA
python3_discogs_client-2.7.1.dist-info/WHEEL
python3_discogs_client-2.7.1.dist-info/top_level.txt
python3_discogs_client-2.7.1.dist-info/RECORD
