Metadata-Version: 2.1
Name: python3-discogs-client
Version: 2.7.1
Summary: Python API client for Discogs
Home-page: https://github.com/joalla/discogs_client
Author: joalla
Author-email: jt@peek-a-boo.at
Classifier: Development Status :: 5 - Production/Stable
Classifier: Environment :: Console
Classifier: License :: OSI Approved :: BSD License
Classifier: Natural Language :: English
Classifier: Operating System :: OS Independent
Classifier: Programming Language :: Python
Classifier: Topic :: Communications
Classifier: Topic :: Utilities
License-File: LICENSE
Requires-Dist: requests
Requires-Dist: oauthlib
Requires-Dist: python-dateutil
Provides-Extra: docs
Requires-Dist: sphinx ; extra == 'docs'
Requires-Dist: pydata-sphinx-theme ; extra == 'docs'
Requires-Dist: myst-parser ; extra == 'docs'
